remapper-1.0.2.dist-info/METADATA
remapper-1.0.2.dist-info/WHEEL
remapper-1.0.2.dist-info/entry_points.txt
remapper-1.0.2.dist-info/licenses/LICENSE
remapper/__init__.py
remapper/py.typed
remapper/remap.py
remapper-1.0.2.dist-info/RECORD
