Metadata-Version: 2.4
Name: remapper
Version: 1.0.2
Summary: Transform objects to and from similar structural mappings.
Keywords: mapping,dataclass,presentation,models,util
Author-Email: Elias Gabriel <oss@eliasfgabriel.com>
License-Expression: BSD-3-Clause-Clear
License-File: LICENSE
Classifier: Development Status :: 5 - Production/Stable
Classifier: Intended Audience :: Developers
Classifier: Topic :: Software Development :: Libraries
Classifier: Topic :: Utilities
Classifier: Programming Language :: Python :: 3
Classifier: Programming Language :: Python :: 3.8
Classifier: Programming Language :: Python :: 3.9
Classifier: Programming Language :: Python :: 3.10
Classifier: Programming Language :: Python :: 3.11
Classifier: Programming Language :: Python :: 3.12
Classifier: Programming Language :: Python :: 3.13
Project-URL: homepage, https://github.com/thearchitector/remapper
Project-URL: source, https://github.com/thearchitector/remapper
Project-URL: changelog, https://github.com/thearchitector/remapper/releases
Project-URL: issues, https://github.com/thearchitector/remapper/issues
Requires-Python: >=3.8
